{
  "continuity_log": [
    {
      "timestamp": "2025-06-20T16:59:53.983600",
      "guard_active": true,
      "core_files_validation": {
        "build_tracker.md": true,
        "build_status.json": true,
        "system_tree.json": true,
        "patch_registry.json": true
      },
      "continuity_status": {
        "timestamp": "2025-06-20T16:59:53.982417",
        "guard_version": "v1.0",
        "system_mode": "quarantined_compliance_enforcer",
        "last_phase_completed": 101,
        "modules_exist_and_complete": 153,
        "build_continuity": "UNKNOWN"
      },
      "build_history": {
        "phases_completed": [],
        "modules_created": [],
        "last_major_action": "Architecture Status Generation",
        "recovery_operations": [
          "Module Recovery Engine Executed",
          "Orphan Intent Classification Completed"
        ],
        "triage_operations": [
          "Emergency Triage Completed"
        ]
      },
      "action_assessment": {
        "timestamp": "2025-06-20T16:59:53.983586",
        "requested_action": "create",
        "target_module": "test_module",
        "recommended_action": "WAIT_FOR_MODE_CHANGE",
        "reasoning": [
          "Action 'create' not allowed in current system mode"
        ],
        "preconditions_met": false,
        "should_proceed": false
      },
      "enforcement_result": {
        "action_allowed": false,
        "recommended_action": "WAIT_FOR_MODE_CHANGE",
        "reasoning": [
          "Action 'create' not allowed in current system mode"
        ],
        "next_steps": [
          "Complete prerequisite: WAIT_FOR_MODE_CHANGE",
          "Re-run build continuity check",
          "Address system mode restrictions",
          "Ensure compliance with architect mode"
        ]
      }
    }
  ]
}